README-public-pypi.md
cisco_radkit_client-1.9.2.dist-info/METADATA
cisco_radkit_client-1.9.2.dist-info/WHEEL
cisco_radkit_client-1.9.2.dist-info/entry_points.txt
cisco_radkit_client-1.9.2.dist-info/licenses/LICENSE.md
radkit_client/LICENSE.html
radkit_client/LICENSE.md
radkit_client/__init__.py
radkit_client/__main__.py
radkit_client/async_/__init__.py
radkit_client/async_/__init__.pyi
radkit_client/async_/admin_client.py
radkit_client/async_/admin_client.pyi
radkit_client/async_/auto_incrementing_id.py
radkit_client/async_/auto_incrementing_id.pyi
radkit_client/async_/client.py
radkit_client/async_/client.pyi
radkit_client/async_/cloud_connections.py
radkit_client/async_/cloud_connections.pyi
radkit_client/async_/context.py
radkit_client/async_/context.pyi
radkit_client/async_/decoders.py
radkit_client/async_/decoders.pyi
radkit_client/async_/device.py
radkit_client/async_/device.pyi
radkit_client/async_/device_flow.py
radkit_client/async_/device_flow.pyi
radkit_client/async_/event_loop_thread.py
radkit_client/async_/event_loop_thread.pyi
radkit_client/async_/exceptions.py
radkit_client/async_/exceptions.pyi
radkit_client/async_/exec/__init__.py
radkit_client/async_/exec/__init__.pyi
radkit_client/async_/exec/exceptions.py
radkit_client/async_/exec/exceptions.pyi
radkit_client/async_/exec/filter.py
radkit_client/async_/exec/filter.pyi
radkit_client/async_/exec/reactive.py
radkit_client/async_/exec/reactive.pyi
radkit_client/async_/exec/state.py
radkit_client/async_/exec/state.pyi
radkit_client/async_/exec/status.py
radkit_client/async_/exec/status.pyi
radkit_client/async_/exec/views.py
radkit_client/async_/exec/views.pyi
radkit_client/async_/formatting/__init__.py
radkit_client/async_/formatting/__init__.pyi
radkit_client/async_/formatting/smart_repr.py
radkit_client/async_/formatting/smart_repr.pyi
radkit_client/async_/formatting/style.py
radkit_client/async_/formatting/style.pyi
radkit_client/async_/formatting/to_json.py
radkit_client/async_/formatting/to_json.pyi
radkit_client/async_/formatting/utils.py
radkit_client/async_/formatting/utils.pyi
radkit_client/async_/http.py
radkit_client/async_/http.pyi
radkit_client/async_/integrated.py
cisco_radkit_client-1.9.2.dist-info/RECORD
