Metadata-Version: 2.1
Name: cisco_radkit_client
Version: 1.9.2
Summary: Cisco RADKit Client
Keywords: cisco,remote,automation
Author-Email: "Cisco Systems Inc." <radkit@cisco.com>
License: Cisco Remote Automation Development Kit (RADKit) -- Copyright (c) 2018-2025 by Cisco Systems, Inc.
Classifier: Development Status :: 5 - Production/Stable
Classifier: Development Status :: 6 - Mature
Classifier: Intended Audience :: Developers
Classifier: Intended Audience :: Information Technology
Classifier: Intended Audience :: System Administrators
Classifier: Intended Audience :: Telecommunications Industry
Classifier: License :: Other/Proprietary License
Classifier: Operating System :: MacOS
Classifier: Operating System :: Microsoft :: Windows
Classifier: Operating System :: POSIX :: Linux
Classifier: Programming Language :: Python :: 3 :: Only
Classifier: Programming Language :: Python :: 3.10
Classifier: Programming Language :: Python :: 3.11
Classifier: Programming Language :: Python :: 3.12
Classifier: Programming Language :: Python :: 3.13
Classifier: Programming Language :: Python :: Implementation :: CPython
Classifier: Topic :: System :: Systems Administration
Project-URL: HomePage, https://radkit.cisco.com
Project-URL: Documentation, https://radkit.cisco.com/docs/index.html
Requires-Python: <3.14,>=3.10
Requires-Dist: cisco_radkit_common==1.9.2
Requires-Dist: tabulate<1.0,>=0.8.10
Requires-Dist: ptpython<4.0,>=3.0.31
Requires-Dist: prompt-toolkit<4.0,>=3.0.50
Requires-Dist: aiofiles<24.0.0,>=0.8.0
Requires-Dist: asyncssh[pyOpenSSL]<3.0,>=2.14.2
Requires-Dist: typing-extensions<5.0,>=4.12.2
Requires-Dist: pexpect<5.0,>=4.9
Requires-Dist: click!=8.1.0,!=8.1.4,!=8.1.5,<8.2.0,>=8.0.1
Requires-Dist: fastapi<1.0,>=0.92.0
Requires-Dist: httpx>=0.26.0
Requires-Dist: h11>=0.13
Requires-Dist: h2<4.4.0,>3.1.0
Requires-Dist: wsproto<1.3.0,>=0.14.0
Requires-Dist: asn1crypto>=1.3.0
Provides-Extra: integrated
Requires-Dist: cisco_radkit_service==1.9.2; extra == "integrated"
